genetable/__init__.py
genetable/datasets.py
genetable/entrez.py
genetable/geneTable.py
genetable/getSeqs.py
genetable/getgenomes.py
genetable/lookSRA.py
genetable/lookgenomes.py
genetable/utils.py
genetable-0.6.dist-info/LICENSE
genetable-0.6.dist-info/METADATA
genetable-0.6.dist-info/WHEEL
genetable-0.6.dist-info/entry_points.txt
genetable-0.6.dist-info/top_level.txt
genetable-0.6.dist-info/RECORD
