Metadata-Version: 2.1
Name: genetable
Version: 0.6
Summary: UNKNOWN
Home-page: https://github.com/Ulises-Rosas/geneTable
Author: Ulises Rosas
Author-email: ulisesfrosasp@gmail.com
License: UNKNOWN
Platform: UNKNOWN
Classifier: Programming Language :: Python :: 3
Classifier: License :: OSI Approved :: MIT License
License-File: LICENSE
Requires-Dist: requests
